{
  "songInfo": {
    "title": "Back in Black",
    "artist": "AC/DC",
    "album": "Back in Black",
    "year": 1980,
    "genre": "Hard Rock",
    "duration": "4:14",
    "difficulty": "Intermediate",
    "tuning": "Standard (EADGBE)",
    "key": "E Major",
    "tempo": 93,
    "timeSignature": "4/4"
  },
  "musicalAnalysis": {
    "overview": "Back in Black is AC/DC's quintessential hard rock anthem, featuring Brian Johnson's debut with the band. The song showcases the Malcolm Young/Angus Young dual guitar approach with simple but effective power chord progressions and memorable melodic hooks.",
    "keySignature": "E Major",
    "chordProgression": [
      {
        "section": "Main Riff",
        "progression": "E5 - D5 - A5 - E5",
        "romanNumerals": "I - bVII - IV - I",
        "description": "Classic rock progression with characteristic bVII chord giving it the AC/DC edge"
      },
      {
        "section": "Verse",
        "progression": "E5 - A5 - E5",
        "romanNumerals": "I - IV - I",
        "description": "Simple I-IV movement typical of AC/DC's straightforward approach"
      },
      {
        "section": "Chorus",
        "progression": "E5 - A5 - B5 - E5",
        "romanNumerals": "I - IV - V - I",
        "description": "Classic I-IV-V-I progression, the backbone of rock music"
      }
    ],
    "scales": [
      {
        "name": "E Minor Pentatonic",
        "notes": ["E", "G", "A", "B", "D"],
        "usage": "Primary scale for lead guitar work and solos",
        "fretboardPattern": "12th fret position (E shape)"
      },
      {
        "name": "E Major Scale",
        "notes": ["E", "F#", "G#", "A", "B", "C#", "D#"],
        "usage": "Chord construction and harmonic analysis",
        "fretboardPattern": "Open position and 12th fret"
      }
    ],
    "modalInterchange": [],
    "keyChanges": []
  },
  "techniques": [
    {
      "name": "Power Chords",
      "difficulty": "Beginner",
      "description": "The foundation of AC/DC's sound - two-note power chords with perfect fifth intervals",
      "details": {
        "chords": ["E5", "A5", "D5", "B5"],
        "tips": [
          "Keep wrist straight and relaxed",
          "Mute unused strings with fretting hand",
          "Use downstrokes for authentic AC/DC tone",
          "Practice clean chord changes at slow tempo"
        ],
        "progression": "E5 - D5 - A5 - E5"
      }
    },
    {
      "name": "Palm Muting",
      "difficulty": "Intermediate",
      "description": "Essential percussive technique using the palm to dampen strings for tight, punchy rhythm",
      "details": {
        "chords": ["E5", "A5"],
        "tips": [
          "Rest palm edge lightly on strings near bridge",
          "Don't press too hard - strings should still ring",
          "Alternate between muted and open for dynamics",
          "Practice with a metronome for tight timing"
        ],
        "progression": "Palm muted E5 - Open A5 - Palm muted E5"
      }
    }
  ],
  "sections": [
    {
      "name": "Intro",
      "timeStamp": "0:00-0:18",
      "description": "Iconic opening riff that immediately establishes the song's driving energy",
      "chords": ["E5", "D5", "A5"],
      "technique": "Power Chords",
      "tab": "(12.1 14.2 14.3).4 (10.1 12.2 12.3).4 (7.1 9.2 9.3).4 (12.1 14.2 14.3).4 |",
      "progression": "E5 - D5 - A5 - E5",
      "notes": [
        "Clean, precise chord changes",
        "Consistent downstroke attack",
        "Let each chord ring briefly before the next"
      ]
    },
    {
      "name": "Verse",
      "timeStamp": "0:18-0:50",
      "description": "Brian Johnson's vocal entrance over palm-muted power chords",
      "chords": ["E5", "A5"],
      "technique": "Palm Muting",
      "tab": "(12.1 14.2 14.3).8*4 (7.1 9.2 9.3).8*4 (12.1 14.2 14.3).8*4 |",
      "progression": "E5 - A5 - E5",
      "notes": [
        "Palm mute the E5 chords for percussive effect",
        "Let A5 ring more openly for contrast",
        "Maintain steady eighth-note rhythm"
      ]
    },
    {
      "name": "Chorus",
      "timeStamp": "0:50-1:22",
      "description": "The anthemic 'Back in Black' hook with full power chord progression",
      "chords": ["E5", "A5", "B5"],
      "technique": "Power Chords",
      "tab": "(12.1 14.2 14.3).4 (7.1 9.2 9.3).4 (9.1 11.2 11.3).4 (12.1 14.2 14.3).4 |",
      "progression": "E5 - A5 - B5 - E5",
      "notes": [
        "Full, ringing power chords",
        "Strong downstroke attack on beat 1",
        "Classic I-IV-V-I progression"
      ]
    },
    {
      "name": "Guitar Solo",
      "timeStamp": "2:24-2:56",
      "description": "Angus Young's signature pentatonic solo with characteristic bends and vibrato",
      "chords": ["E5", "A5", "B5"],
      "technique": "Lead Guitar",
      "tab": "12.2 15.2 12.2 14.2 12.2 | 15.2b17 15.2 12.2 14.2 12.2 | 12.1 15.1 12.1 14.1 12.1 |",
      "progression": "Over E5 - A5 - B5 - E5",
      "notes": [
        "Use E minor pentatonic scale",
        "Focus on bending accuracy",
        "Add vibrato to sustained notes",
        "Keep phrasing simple but effective"
      ]
    }
  ],
  "equipment": {
    "guitar": {
      "recommended": "Gibson SG Standard",
      "pickup": "Humbucker (Bridge position)",
      "alternatives": [
        "Gibson Les Paul Standard",
        "Epiphone SG Standard",
        "Any guitar with humbuckers"
      ]
    },
    "amp": {
      "recommended": "Marshall Super Lead 100W",
      "settings": {
        "gain": "6-7",
        "treble": "7",
        "middle": "6",
        "bass": "5",
        "presence": "5"
      },
      "alternatives": [
        "Marshall JCM800",
        "Marshall DSL100H",
        "Any high-gain tube amp"
      ]
    },
    "effects": {
      "distortion": "Natural tube saturation from cranked Marshall",
      "reverb": "Minimal room reverb",
      "other": "None - straight guitar into amp"
    }
  },
  "learningPath": {
    "beginner": {
      "title": "Learn the Main Riff",
      "timeEstimate": "2-3 weeks",
      "skills": [
        "Basic power chord shapes (E5, A5, D5)",
        "Clean chord transitions",
        "Consistent downstroke technique",
        "Basic rhythm and timing"
      ]
    },
    "intermediate": {
      "title": "Add Dynamics and Technique",
      "timeEstimate": "3-4 weeks",
      "skills": [
        "Palm muting technique",
        "Verse/chorus dynamic contrast",
        "Proper string muting",
        "Playing with backing track"
      ]
    },
    "advanced": {
      "title": "Master the Solo",
      "timeEstimate": "4-6 weeks",
      "skills": [
        "E minor pentatonic scale mastery",
        "String bending accuracy",
        "Vibrato technique",
        "Complete song performance"
      ]
    }
  },
  "practiceNotes": {
    "commonMistakes": [
      "Playing too fast initially - focus on clean execution",
      "Not muting properly between chord changes",
      "Overcomplicating the simple power chord approach",
      "Using upstrokes instead of consistent downstrokes"
    ],
    "practiceRoutine": [
      "Start with isolated power chord practice",
      "Practice main riff at 60 BPM, gradually increase",
      "Work on palm muting with metronome",
      "Practice complete song with backing track"
    ],
    "metronomeWork": [
      "Practice main riff at 70 BPM (slow)",
      "Build up to 85 BPM (performance tempo)",
      "Work on palm muting patterns at various tempos",
      "Practice chord changes with click track"
    ]
  },
  "relatedSongs": {
    "acdc": [
      {
        "title": "Highway to Hell",
        "similarity": "Similar power chord approach and rhythm patterns",
        "link": "/lessons/songs/song-analysis/highway-to-hell"
      },
      {
        "title": "Thunderstruck",
        "similarity": "Iconic opening riff and aggressive power chord style",
        "link": "/lessons/songs/song-analysis/thunderstruck"
      },
      {
        "title": "T.N.T.",
        "similarity": "Classic AC/DC power chord progression and structure"
      }
    ],
    "similarTechniques": [
      {
        "title": "Smoke on the Water",
        "artist": "Deep Purple",
        "technique": "Power Chords",
        "similarity": "Essential power chord riff, similar difficulty level"
      },
      {
        "title": "Iron Man",
        "artist": "Black Sabbath",
        "technique": "Palm Muting",
        "similarity": "Heavy palm muting and power chord combination"
      },
      {
        "title": "Paranoid",
        "artist": "Black Sabbath",
        "technique": "Fast Power Chords",
        "similarity": "Quick power chord changes and downstroke technique"
      }
    ]
  }
}
